{
  "project_info": {
    "project_number": "579767934368",
    "project_id": "wataburger-a5b6c",
    "storage_bucket": "wataburger-a5b6c.appspot.com"
  },
  "client": [
    {
      "client_info": {
        "mobilesdk_app_id": "1:579767934368:android:87347d1442a8cea7bb58c5",
        "android_client_info": {
          "package_name": "com.anet.wataburger"
        }
      },
      "oauth_client": [],
      "api_key": [
        {
          "current_key": "AIzaSyAI9zp6KkbfzyI1UM9Z1ePm_9vQUeKFQ-I"
        }
      ],
      "services": {
        "appinvite_service": {
          "other_platform_oauth_client": []
        }
      }
    }
  ],
  "configuration_version": "1"
}